sqlServerPlugin/__init__.py
sqlServerPlugin/sqlServerPlugin.py
dbfaker_sqlserver_plugin-0.1.1.dist-info/METADATA
dbfaker_sqlserver_plugin-0.1.1.dist-info/WHEEL
dbfaker_sqlserver_plugin-0.1.1.dist-info/top_level.txt
dbfaker_sqlserver_plugin-0.1.1.dist-info/RECORD
