Metadata-Version: 2.1
Name: dbfaker-sqlserver-plugin
Version: 0.1.1
Summary: An project to make fake data dump based on sqlserver database.
Home-page: UNKNOWN
Author: lucaslima18
Author-email: lucas.ala1999@gmail.com
License: UNKNOWN
Platform: UNKNOWN
Requires-Python: >=3.8,<4.0
